{
  "to": "quest@edmondo.jp",
  "subject": "エドモンド プログラミングスクール 世田谷校様、ホームページで「自由が丘 プログラミングスクール」の検索に出ませんか？",
  "body": "エドモンド プログラミングスクール 世田谷校\nご担当者様\n\nはじめまして。\nHNH Design Worksの豊川です。ビジネスの可能性をWebで最大化する、をコンセプトにHP制作をしています。\n\nGoogleマップでエドモンド プログラミングスクール 世田谷校様を拝見しました。\nカリキュラムや受講生の声を、モダンなデザインでアピールできます。\n\n「自由が丘 プログラミングスクール」で検索したとき、公式サイトがないと\n新しいお客様に見つけてもらう機会を逃しているかもしれません。\n\n普段こういうサイトを作っています：\nhttps://hnh-design-works.vercel.app\n\n今ちょうどキャンペーン中で、通常よりお得にご依頼いただけます。\nこちらのフォーム（3分くらいです）からお店の情報を教えていただければ、\n打ち合わせなしで制作を進められます：\nhttps://hnh-design-works.vercel.app/intake.html\n\nご興味なければスルーで構いません。\nお忙しいところ失礼しました。\n\n──────────────────\nHNH Design Works\n豊川 直也\nhnh.designworks@gmail.com\n──────────────────\n\n※Googleマップの公開情報をもとにご連絡しております。\n※ご不要の場合はご返信いただければ即時停止いたします。",
  "shop_name": "エドモンド プログラミングスクール 世田谷校",
  "category": "プログラミングスクール",
  "area": "自由が丘",
  "phone": "090-3600-9190",
  "created_at": "2026-04-08T18:34:00.659Z",
  "status": "queued",
  "type": "initial"
}